freezer_ui/__init__.py
freezer_ui/dashboard.py
freezer_ui/models.py
freezer_ui/urls.py
freezer_ui/utils.py
freezer_ui/version.py
freezer_ui/actions/__init__.py
freezer_ui/actions/panel.py
freezer_ui/actions/tables.py
freezer_ui/actions/urls.py
freezer_ui/actions/views.py
freezer_ui/actions/templates/actions/_action.html
freezer_ui/actions/templates/actions/_advanced.html
freezer_ui/actions/templates/actions/_rules.html
freezer_ui/actions/templates/actions/_snapshot.html
freezer_ui/actions/templates/actions/detail.html
freezer_ui/actions/templates/actions/index.html
freezer_ui/actions/workflows/__init__.py
freezer_ui/actions/workflows/action.py
freezer_ui/api/__init__.py
freezer_ui/api/api.py
freezer_ui/api/rest/__init__.py
freezer_ui/api/rest/rest_api.py
freezer_ui/api/rest/urls.py
freezer_ui/backups/__init__.py
freezer_ui/backups/panel.py
freezer_ui/backups/tables.py
freezer_ui/backups/urls.py
freezer_ui/backups/views.py
freezer_ui/backups/templates/backups/detail.html
freezer_ui/backups/templates/backups/index.html
freezer_ui/backups/templates/backups/restore.html
freezer_ui/backups/workflows/__init__.py
freezer_ui/backups/workflows/restore.py
freezer_ui/clients/__init__.py
freezer_ui/clients/panel.py
freezer_ui/clients/tables.py
freezer_ui/clients/urls.py
freezer_ui/clients/views.py
freezer_ui/clients/templates/clients/detail.html
freezer_ui/clients/templates/clients/index.html
freezer_ui/enabled/_5050_freezer.py
freezer_ui/enabled/__init__.py
freezer_ui/jobs/__init__.py
freezer_ui/jobs/browsers.py
freezer_ui/jobs/panel.py
freezer_ui/jobs/tables.py
freezer_ui/jobs/urls.py
freezer_ui/jobs/views.py
freezer_ui/jobs/templates/jobs/_actions.html
freezer_ui/jobs/templates/jobs/_info.html
freezer_ui/jobs/templates/jobs/browser.html
freezer_ui/jobs/workflows/__init__.py
freezer_ui/jobs/workflows/actions.py
freezer_ui/jobs/workflows/create.py
freezer_ui/jobs/workflows/update_actions.py
freezer_ui/jobs/workflows/update_job.py
freezer_ui/locale/de/LC_MESSAGES/django.po
freezer_web_ui-17.0.0.dist-info/AUTHORS
freezer_web_ui-17.0.0.dist-info/LICENSE
freezer_web_ui-17.0.0.dist-info/METADATA
freezer_web_ui-17.0.0.dist-info/WHEEL
freezer_web_ui-17.0.0.dist-info/pbr.json
freezer_web_ui-17.0.0.dist-info/top_level.txt
freezer_web_ui-17.0.0.dist-info/RECORD
