Metadata-Version: 2.1
Name: freezer-web-ui
Version: 17.0.0
Summary: Freezer - Backup as a Service User Interface
Home-page: https://docs.openstack.org/freezer/latest/
Author: OpenStack
Author-email: openstack-discuss@lists.openstack.org
License: Apache-2.0
Keywords: horizon,freezer,backup,openstack
Classifier: Development Status :: 5 - Production/Stable
Classifier: Environment :: OpenStack
Classifier: Framework :: Django
Classifier: Intended Audience :: Developers
Classifier: Intended Audience :: Information Technology
Classifier: Intended Audience :: System Administrators
Classifier: Operating System :: OS Independent
Classifier: Operating System :: POSIX :: Linux
Classifier: Programming Language :: Python
Classifier: Programming Language :: Python :: Implementation :: CPython
Classifier: Programming Language :: Python :: 3 :: Only
Classifier: Programming Language :: Python :: 3
Classifier: Programming Language :: Python :: 3.8
Classifier: Programming Language :: Python :: 3.9
Classifier: Programming Language :: Python :: 3.10
Classifier: Programming Language :: Python :: 3.11
Classifier: Programming Language :: Python :: 3.12
Classifier: Topic :: Internet :: WWW/HTTP
Requires-Python: >=3.8
License-File: LICENSE
License-File: AUTHORS
Requires-Dist: python-freezerclient >=2.0.0
Requires-Dist: oslo.log >=3.36.0
Requires-Dist: horizon >=17.1.0
